oblif/__init__.py
oblif/compat.py
oblif/context.py
oblif/decorator.py
oblif/iterators.py
oblif/types.py
oblif/values.py
oblif-0.3.1.dist-info/LICENSE
oblif-0.3.1.dist-info/METADATA
oblif-0.3.1.dist-info/WHEEL
oblif-0.3.1.dist-info/top_level.txt
oblif-0.3.1.dist-info/RECORD
